django_docopt_command/__init__.py
django_docopt_command/command.py
django_docopt_command-1.1.0.dist-info/LICENSE.rst
django_docopt_command-1.1.0.dist-info/METADATA
django_docopt_command-1.1.0.dist-info/WHEEL
django_docopt_command-1.1.0.dist-info/top_level.txt
django_docopt_command-1.1.0.dist-info/RECORD
