Metadata-Version: 2.1
Name: django-docopt-command
Version: 1.1.0
Summary: Django-docopt-command allows you to write Django manage.py commands using the docopt library.
Home-page: https://github.com/mbraak/django-docopt-command
Author: Marco Braak
Author-email: mbraak@ridethepony.nl
License: Apache License, Version 2.0
Platform: UNKNOWN
Classifier: Development Status :: 5 - Production/Stable
Classifier: Framework :: Django
Classifier: Framework :: Django :: 2.2
Classifier: Framework :: Django :: 3.0
Classifier: Framework :: Django :: 3.1
Classifier: Intended Audience :: Developers
Classifier: License :: OSI Approved :: Apache Software License
Classifier: Programming Language :: Python :: 3.6
Classifier: Programming Language :: Python :: 3.7
Classifier: Programming Language :: Python :: 3.8
Classifier: Programming Language :: Python :: Implementation :: CPython
Requires-Dist: docopt
